{
  "pages": [
    {
      "path": "pages/home/index",
      "style": {
        "navigationBarTitleText": "首页"
      }
    },
    {
      "path": "pages/order/index",
      "style": {
        "navigationBarTitleText": "订单"
      }
    },
    {
      "path": "pages/my/index",
      "style": {
        "navigationBarTitleText": "我的"
      }
    }
  ],
	"globalStyle": {
		"navigationBarTextStyle": "black",
		"navigationBarTitleText": "uni-app",
		"navigationBarBackgroundColor": "#F8F8F8",
		"backgroundColor": "#F8F8F8"
	},
  "easycom": {
    "autoscan": true,
    "custom": {
            "^uni-(.*)": "@dcloudio/uni-ui/lib/uni-$1/uni-$1.vue"
    }
  }
}
